Metadata-Version: 2.3
Name: truss
Version: 0.60.0
Summary: A seamless bridge from model development to model delivery
License: MIT
Keywords: MLOps,AI,Model Serving,Model Deployment,Machine Learning
Author: Pankaj Gupta
Author-email: pankaj@baseten.co
Requires-Python: >=3.8,<3.13
Classifier: License :: OSI Approved :: MIT License
Classifier: Programming Language :: Python :: 3
Classifier: Programming Language :: Python :: 3.8
Classifier: Programming Language :: Python :: 3.9
Classifier: Programming Language :: Python :: 3.10
Classifier: Programming Language :: Python :: 3.11
Classifier: Programming Language :: Python :: 3.12
Provides-Extra: all
Requires-Dist: Jinja2 (>=3.1.2,<4.0.0)
Requires-Dist: PyYAML (>=6.0)
Requires-Dist: aiofiles (>=24.1.0,<25.0.0)
Requires-Dist: aiohttp (>=3.10.10,<4.0.0)
Requires-Dist: blake3 (>=0.3.3,<0.4.0)
Requires-Dist: boto3 (>=1.34.85,<2.0.0)
Requires-Dist: click (>=8.0.3,<9.0.0)
Requires-Dist: fastapi (>=0.109.1)
Requires-Dist: google-cloud-storage (==2.10.0)
Requires-Dist: httpx (>=0.24.1)
Requires-Dist: huggingface_hub (>=0.25.0)
Requires-Dist: inquirerpy (>=0.3.4,<0.4.0)
Requires-Dist: libcst (<1.2.0)
Requires-Dist: loguru (>=0.7.2)
Requires-Dist: packaging (>=20.9)
Requires-Dist: pathspec (>=0.9.0)
Requires-Dist: psutil (>=5.9.4)
Requires-Dist: pydantic (>=1.10.0)
Requires-Dist: python-json-logger (>=2.0.2)
Requires-Dist: python-on-whales (>=0.68.0,<0.69.0)
Requires-Dist: requests (>=2.31)
Requires-Dist: rich (>=13.4.2,<14.0.0)
Requires-Dist: rich-click (>=1.6.1,<2.0.0)
Requires-Dist: ruff (>=0.4.8)
Requires-Dist: single-source (>=0.3.0,<0.4.0)
Requires-Dist: tenacity (>=8.0.1,<9.0.0)
Requires-Dist: watchfiles (>=0.19.0,<0.20.0)
Project-URL: Bug Reports, https://github.com/basetenlabs/truss/issues
Project-URL: Baseten, https://baseten.co
Project-URL: Documentation, https://truss.baseten.co
Project-URL: Homepage, https://truss.baseten.co
Project-URL: Repository, https://github.com/basetenlabs/truss
